{"Modules":[{"Key":"","Source":"","Dir":"."},{"Key":"app_service","Source":"git::https://github.com/Olisehgenesis/modules.git//app_service","Dir":".terraform/modules/app_service/app_service"},{"Key":"app_service.app_service","Source":"git::https://github.com/Olisehgenesis/modules.git","Dir":".terraform/modules/app_service.app_service"},{"Key":"app_service_plan","Source":"git::https://github.com/Olisehgenesis/modules.git//app_service_plan","Dir":".terraform/modules/app_service_plan/app_service_plan"},{"Key":"application_insights","Source":"git::https://github.com/Olisehgenesis/modules.git//application_insights","Dir":".terraform/modules/application_insights/application_insights"},{"Key":"key_vault","Source":"git::https://github.com/Olisehgenesis/modules.git//key_vault","Dir":".terraform/modules/key_vault/key_vault"},{"Key":"log_analytics","Source":"git::https://github.com/Olisehgenesis/modules.git//log_analytics","Dir":".terraform/modules/log_analytics/log_analytics"},{"Key":"static_app","Source":"git::https://github.com/Olisehgenesis/modules.git//static_app","Dir":".terraform/modules/static_app/static_app"},{"Key":"static_web_app","Source":"git::https://github.com/Olisehgenesis/modules.git//static_web_app","Dir":".terraform/modules/static_web_app/static_web_app"},{"Key":"storage_account","Source":"git::https://github.com/Olisehgenesis/modules.git//storage_account","Dir":".terraform/modules/storage_account/storage_account"}]}